scriptdoctest.py
scripttest.py
scriptdoctest-0.3.dist-info/DESCRIPTION.rst
scriptdoctest-0.3.dist-info/METADATA
scriptdoctest-0.3.dist-info/RECORD
scriptdoctest-0.3.dist-info/WHEEL
scriptdoctest-0.3.dist-info/metadata.json
scriptdoctest-0.3.dist-info/top_level.txt
