Metadata-Version: 2.0
Name: scriptdoctest
Version: 0.3
Summary: Helper to test interactive shell
Home-page: https://github.com/Anaphory/scriptdoctest
Author: Gereon Kaiping
Author-email: gereon.kaiping@gmail.com
License: MIT
Keywords: test doctest command line scripts tutorial
Platform: UNKNOWN
Classifier: Development Status :: 3 - Alpha
Classifier: Intended Audience :: Developers
Classifier: License :: OSI Approved :: MIT License
Classifier: Topic :: Documentation
Classifier: Topic :: Software Development :: Testing
Classifier: Topic :: Software Development :: Documentation
Classifier: Topic :: System :: Shells
Classifier: Programming Language :: Python :: 2
Classifier: Programming Language :: Python :: 3
